aioh/__init__.py
aioh/limited_concurrency.py
aioh-0.0.0.dist-info/METADATA
aioh-0.0.0.dist-info/WHEEL
aioh-0.0.0.dist-info/licenses/LICENSE
aioh-0.0.0.dist-info/RECORD
