Metadata-Version: 2.3
Name: aioh
Version: 0.0.0
Summary: Add your description here
License-File: LICENSE
Requires-Python: >=3.9
